{"updatedAt":"2026-07-14T09:33:40.571Z","sampleRaces":2942,"winners":[{"roi":103.8,"hitRate":10.9,"avgPoints":2,"races":64,"patternId":"p_1_23","patternName":"1着1位/相手2-3位(2点)","filterName":"スコア66+","cond":{"scoreMin":66}}],"results":[{"pattern":"1着1位/相手2-3位(2点)","filter":"スコア66+","races":64,"avgPoints":2,"hitRate":10.9,"roi":103.8,"profit":480},{"pattern":"1着1位/2着2-3位/3着2-4位(4点)","filter":"スコア66+","races":64,"avgPoints":4,"hitRate":18.8,"roi":90.5,"profit":-2430},{"pattern":"1着1位/2着2-4位/3着2-5位","filter":"スコア66+","races":64,"avgPoints":9,"hitRate":37.5,"roi":71.7,"profit":-16290},{"pattern":"1着1位/相手2-5位","filter":"スコア66+","races":64,"avgPoints":12,"hitRate":40.6,"roi":68.3,"profit":-24320},{"pattern":"1着1位/2着2-3位/3着2-4位(4点)","filter":"ガールズのみ","races":287,"avgPoints":4,"hitRate":28.6,"roi":66.7,"profit":-38240},{"pattern":"1着1位/2着2-3位/3着2-4位(4点)","filter":"スコア64+","races":118,"avgPoints":4,"hitRate":16.1,"roi":66.3,"profit":-15890},{"pattern":"1着1位/2着2-4位/3着2-5位","filter":"ガールズのみ","races":287,"avgPoints":9,"hitRate":44.3,"roi":65.4,"profit":-89460},{"pattern":"1着1位/相手2-3位(2点)","filter":"スコア64+","races":118,"avgPoints":2,"hitRate":8.5,"roi":65.1,"profit":-8230},{"pattern":"1着1位/相手2-3位(2点)","filter":"スコア60+かつS級除外","races":264,"avgPoints":2,"hitRate":8,"roi":63.7,"profit":-19160},{"pattern":"1着1位/相手2-3位(2点)","filter":"◎のみ","races":274,"avgPoints":2,"hitRate":8,"roi":63,"profit":-20300},{"pattern":"1着1位/相手2-3位(2点)","filter":"◎のみ+ガ除外","races":274,"avgPoints":2,"hitRate":8,"roi":63,"profit":-20300},{"pattern":"1着1位/相手2-5位","filter":"スコア62+","races":154,"avgPoints":12,"hitRate":37.7,"roi":62.8,"profit":-68810},{"pattern":"現行(1着1位固定/相手2-4位)","filter":"ガールズのみ","races":287,"avgPoints":6,"hitRate":35.2,"roi":62.3,"profit":-65000},{"pattern":"1着1位/相手2-3位(2点)","filter":"スコア60+","races":281,"avgPoints":2,"hitRate":7.8,"roi":61.4,"profit":-21700},{"pattern":"現行(1着1位固定/相手2-4位)","filter":"スコア66+","races":64,"avgPoints":6,"hitRate":20.3,"roi":61.3,"profit":-14870},{"pattern":"現行(1着1位固定/相手2-4位)","filter":"スコア60+かつS級除外","races":264,"avgPoints":6,"hitRate":20.5,"roi":60.9,"profit":-61960},{"pattern":"現行(1着1位固定/相手2-4位)","filter":"スコア62+かつS級除外","races":146,"avgPoints":6,"hitRate":20.5,"roi":60.5,"profit":-34560},{"pattern":"1着1位/2着2-4位/3着2-5位","filter":"スコア64+","races":118,"avgPoints":9,"hitRate":34.7,"roi":60.3,"profit":-42190},{"pattern":"1着1位/相手2-5位","filter":"スコア64+","races":118,"avgPoints":12,"hitRate":39.8,"roi":60.3,"profit":-56190},{"pattern":"現行(1着1位固定/相手2-4位)","filter":"◎のみ","races":274,"avgPoints":6,"hitRate":21.2,"roi":60.2,"profit":-65480},{"pattern":"現行(1着1位固定/相手2-4位)","filter":"◎のみ+ガ除外","races":274,"avgPoints":6,"hitRate":21.2,"roi":60.2,"profit":-65480},{"pattern":"1着1位/相手2-3位(2点)","filter":"スコア62+かつS級除外","races":146,"avgPoints":2,"hitRate":8.2,"roi":60,"profit":-11670},{"pattern":"1着1位/相手2-3位(2点)","filter":"A級のみスコア58+","races":584,"avgPoints":2,"hitRate":7.4,"roi":59,"profit":-47920},{"pattern":"現行(1着1位固定/相手2-4位)","filter":"スコア64+","races":118,"avgPoints":6,"hitRate":21.2,"roi":58.8,"profit":-29170},{"pattern":"現行(1着1位固定/相手2-4位)","filter":"スコア60+","races":281,"avgPoints":6,"hitRate":20.6,"roi":58.7,"profit":-69680},{"pattern":"現行(1着1位固定/相手2-4位)","filter":"スコア62+","races":154,"avgPoints":6,"hitRate":20.8,"roi":58.6,"profit":-38260},{"pattern":"1着1位/相手2-5位","filter":"ガールズのみ","races":287,"avgPoints":12,"hitRate":48.1,"roi":58.5,"profit":-142850},{"pattern":"1着1位/相手2-3位(2点)","filter":"スコア58+","races":629,"avgPoints":2,"hitRate":7.3,"roi":58.4,"profit":-52270},{"pattern":"1着1位/相手2-3位(2点)","filter":"スコア58+かつガ除外","races":629,"avgPoints":2,"hitRate":7.3,"roi":58.4,"profit":-52270},{"pattern":"1着1位/相手2-3位(2点)","filter":"gap5+かつスコア58+","races":441,"avgPoints":2,"hitRate":8.2,"roi":58.4,"profit":-36710},{"pattern":"1着1位/2着2-3位/3着2-4位(4点)","filter":"スコア62+かつS級除外","races":146,"avgPoints":4,"hitRate":15.1,"roi":58.4,"profit":-24310},{"pattern":"1着1位/2着2-3位/3着2-4位(4点)","filter":"gap5+かつスコア58+","races":441,"avgPoints":4,"hitRate":14.7,"roi":58.2,"profit":-73790},{"pattern":"1着1位/相手2-5位","filter":"スコア62+かつS級除外","races":146,"avgPoints":12,"hitRate":37,"roi":58,"profit":-73570},{"pattern":"1着1位/相手2-3位(2点)","filter":"1位抜け(gap8+)","races":1669,"avgPoints":2,"hitRate":9,"roi":57.9,"profit":-140600},{"pattern":"1着1-2/2着1-3/3着1-5","filter":"ガールズのみ","races":287,"avgPoints":12,"hitRate":48.4,"roi":57.6,"profit":-146000},{"pattern":"1着1位/2着2-4位/3着2-5位","filter":"スコア62+かつS級除外","races":146,"avgPoints":9,"hitRate":31.5,"roi":57.4,"profit":-55980},{"pattern":"1着1位/相手2-3位(2点)","filter":"ガールズのみ","races":287,"avgPoints":2,"hitRate":16.7,"roi":57.2,"profit":-24560},{"pattern":"1着1位/相手2-3位(2点)","filter":"スコア55+","races":1403,"avgPoints":2,"hitRate":7.4,"roi":57.1,"profit":-120440},{"pattern":"1着1位/2着2-3位/3着2-4位(4点)","filter":"スコア62+","races":154,"avgPoints":4,"hitRate":15.6,"roi":57.1,"profit":-26410},{"pattern":"1着1位/相手2-3位(2点)","filter":"スコア62+","races":154,"avgPoints":2,"hitRate":7.8,"roi":56.9,"profit":-13270}]}